llama_index/embeddings/mistralai/__init__.py
llama_index/embeddings/mistralai/base.py
llama_index_embeddings_mistralai-0.4.1.dist-info/METADATA
llama_index_embeddings_mistralai-0.4.1.dist-info/WHEEL
llama_index_embeddings_mistralai-0.4.1.dist-info/licenses/LICENSE
llama_index_embeddings_mistralai-0.4.1.dist-info/RECORD
